summarizer/__init__.py
summarizer/cli.py
summarizer/summarizer.py
summarizer/tests.ipynb
summarizer/utils.py
summarygen-0.1.0.dist-info/LICENSE
summarygen-0.1.0.dist-info/METADATA
summarygen-0.1.0.dist-info/WHEEL
summarygen-0.1.0.dist-info/entry_points.txt
summarygen-0.1.0.dist-info/top_level.txt
summarygen-0.1.0.dist-info/RECORD
