Metadata-Version: 2.1
Name: summarygen
Version: 0.1.0
Summary: A command-line tool for text summarization
Home-page: https://github.com/hwang2006/summarygen
Author: Soonwook Hwang
Author-email: hwang@kisti.re.kr
Classifier: Programming Language :: Python :: 3
Classifier: License :: OSI Approved :: MIT License
Classifier: Operating System :: OS Independent
Requires-Python: >=3.7
License-File: LICENSE
Requires-Dist: click>=8.0.0
Requires-Dist: transformers>=4.0.0
Requires-Dist: torch==2.4.0
Requires-Dist: numpy<2.0
Requires-Dist: beautifulsoup4>=4.9.0
Requires-Dist: requests>=2.25.0
Provides-Extra: dev
Requires-Dist: pytest>=7.0; extra == "dev"
Requires-Dist: pytest-cov>=4.0; extra == "dev"
Requires-Dist: pytest-mock>=3.10.0; extra == "dev"
Requires-Dist: requests-mock>=1.11.0; extra == "dev"
Requires-Dist: black>=22.0.0; extra == "dev"
Requires-Dist: twine>=4.0.0; extra == "dev"
Requires-Dist: build>=0.10.0; extra == "dev"
Requires-Dist: wheel>=0.36.0; extra == "dev"
